Metadata-Version: 2.1
Name: archie-public-test
Version: 0.1.1
Summary: My first Python package
License: UNKNOWN
Platform: UNKNOWN
Classifier: Programming Language :: Python :: 3
Classifier: License :: OSI Approved :: MIT License
Classifier: Operating System :: OS Independent
